Adrscheck/__init__.py
Adrscheck/models/__init__.py
Adrscheck/models/city_handlers/__init__.py
Adrscheck/models/city_handlers/bangalore_handler.py
Adrscheck/models/city_handlers/mumbai_handler.py
Adrscheck/models/city_handlers/mysore_handler.py
Adrscheck/models/city_handlers/pune_handler.py
Adrscheck/models/state_handlers/__init__.py
Adrscheck/models/state_handlers/karnataka_handler.py
Adrscheck/models/state_handlers/maharashtra_handler.py
Adrscheck/models/utils/__init__.py
Adrscheck/models/utils/distance.py
Adrscheck/models/utils/fuzzy_matchings.py
Adrscheck/models/utils/importcsv.py
Adrscheck-1.1.0.dist-info/LICENSE.txt
Adrscheck-1.1.0.dist-info/METADATA
Adrscheck-1.1.0.dist-info/WHEEL
Adrscheck-1.1.0.dist-info/top_level.txt
Adrscheck-1.1.0.dist-info/RECORD
